{
    "hymns": [
        {
            "songTitle": "QUEL SORT MERVEILLEUX",
            "id": 67,
            "songId": 1,
            "chorus": "Sauvé, sauvé, \nSauvé par le sang de l’Agneau! \nSauvé, sauvé, \nÀ jamais un enfant de Dieu!",
            "key": "Sol majeur",
            "author": "F. J. Crosby (1882), W. J. Kirkpatrick (1882)",
            "enLyrics": [
                "Quel sort merveilleux d’être sauvé, \nSauvé par le sang de l’Agneau, \nSauvé par Sa grâce infinie, \nÀ jamais un enfant de Dieu!",
                "Sauvé, quelle joie ineffable! \nDes mots ne peuvent l’exprimer. \nJe sais que Sa douce présence \nM’accompagnera à jamais.",
                "Je pense à mon Sauveur sublime, \nLe louant d’un cœur enchanté. \nJe chante’, je ne peux pas me taire, \nSon amour m’a rendu heureux.",
                "Au ciel réservé par le Maître, \nM’attend la couronne de vie. \nEt joint aux rangs des fidèles, \nJe demeurerai près de Lui.",
                "Je sais, je verrai dans Sa gloire \nLe seul Roi qui règne sur moi; \nEt qui par Sa pleine victoire \nMe rend fort de garder Ses lois."
            ]
        },
        {
            "songTitle": "OH! QUEL BONHEUR DE LE CONNAÎTRE",
            "id": 68,
            "songId": 2,
            "chorus": "Chantons, chantons d’un cœur joyeux \nLe grand amour du Rédempteur, \nQui vint à nous du haut des cieux, \nEt nous sauva du destructeur!",
            "key": "Sol majeur",
            "author": "J. Mac Granahan (1876), A. Glardon (1839-1922)",
            "enLyrics": [
                "Oh! Quel bonheur de Le connaître, \nL’Ami qui ne saurait changer, \nDe L’avoir ici-bas pour Maître, \nPour Défenseur et pour Berger!",
                "Dans la misère et l’ignorance \nNous nous débattions sans espoir, \nLa mort au cœur, l’âme en souffrance, \nQuand à nos yeux Il se fit voir.",
                "Il nous apporta la lumière, \nLa victoire et la liberté. \nL’ennemi mordit la poussière, \nPour toujours satan fut dompté.",
                "Vers l’avenir marchons sans crainte, \nEt sans souci du lendemain, \nPas à pas, nos pieds dans l’empreinte \nDe Ses pieds sur notre chemin."
            ]
        },
        {
            "songTitle": "LE NOM DE JESUS EST SI DOUX",
            "id": 2,
            "songId": 3,
            "chorus": "Jésus! Béni soit Ton nom! \nJésus! Oh merveilleux don! \nJésus! Suprême rançon, \nSois adoré pour toujours.",
            "key": "Si ♭ majeur",
            "author": "Contesse-Vernier, J. Guillod (1885)",
            "enLyrics": [
                "Le nom de Jésus est si doux! \nDe Dieu désarmant le courroux; \nIl nous appelle au rendez-vous, \nPrécieux nom de Jésus!",
                "J’aime ce nom dans le chagrin, \nIl me soutient sur le chemin, \nSa musique est un son divin, \nPrécieux nom de Jésus!",
                "J’aime le nom de mon Sauveur, \nCar Lui seul connaît tout mon cœur; \nLui seul me rend plus que vainqueur, \nPrécieux nom de Jésus!",
                "Et si parfois j’ai succombé, \nSi dans le mal je suis tombé, \nSon nom puissant m’a relevé: \nPrécieux nom de Jésus!"
            ]
        },
        {
            "songTitle": "UN NOM SI DOUX RÉJOUIT MON CŒUR",
            "id": 69,
            "songId": 4,
            "chorus": "Oui j’aime Jésus, (x3) \nQui m’aima le premier.",
            "key": "Fa majeur",
            "author": "American Melody, Frederick Whitfield (1855)",
            "enLyrics": [
                "Un nom si doux réjouit mon cœur, \nMe fait chanter Ses louanges, \nBrille d’une auguste splendeur: \nLe plus beau nom Jésus.",
                "Ce nom parle d’amour suprême, \nDe Lui qui m’a sauvé, \nQui a versé Son sang précieux \nPour ôter mes péchés.",
                "Et Il me parle de ce que \nLe Père a pour l’enfant: \nDe Sa grâce, Son fort Esprit \nPour vaincre à chaque instant.",
                "Et Il affirme qu’un ami \nM’assiste en chaque épreuve, \nQu’Il me soutient dans mon chagrin, \nDe la peine, Il m’enlève.",
                "Il remplit mon cœur d'allégresse, \nIl sèche’ toutes mes larmes; \nEt Il me dit d’une’ voix si douce, \nÔ Mon enfant, Je t’aime.",
                "Toujours, ce Nom aplanira \nLe sentier rocailleux, \nSur le chemin, Il polira, \nTout ce qui est tortueux.",
                "Là-haut avec les Rachetés, \nLibres de tous fardeaux; \nNous chanterons tout apaisés \nLe cantique’ de l’Agneau."
            ]
        },
        {
            "songTitle": "POUSSONS DES CRIS DE JOIE EN ACCORD",
            "id": 418,
            "songId": 5,
            "chorus": "Dieu nous aime. (bis) \nPoussons des cris de joie en accord. \nQue Dieu nous aime",
            "key": "Mi ♭ majeur",
            "author": "Howard Kingsbury (1886)",
            "enLyrics": [
                "Poussons des cris de joie en accord: \nDieu nous aime. \nTerre et ciel, répétez encore : \nDieu nous aime \nAme lassée, relève-toi ! \nJésus t’a sauvé sur la croix. \nCrois-le et chante plein de joie. \nDieu nous aime.",
                "Annoncez jusqu’au bout du monde : \nDieu nous aime \nDites à chacun sans crainte et honte : \nDieu nous aime. \nChrist par son sang nous a rachetés, \nLavés de nos iniquités, \nDe tous nos fers nous a libérés : \nDieu nous aime.",
                "Quel sort remplis de joie ici-bas ! \nDieu nous aime. Guidés par son esprit pas à pas. \nDieu nous aime. \nNotre soleil et bouclier, \nDieu nous garde de tout côté, \nToujours nous rend victorieux. \nDieu nous aime."
            ]
        },
        {
            "songTitle": "TOI QUI DISPOSES",
            "id": 70,
            "songId": 6,
            "chorus": "",
            "key": "Fa majeur",
            "author": "Air Silésien, Blanche Sautter (1890)",
            "enLyrics": [
                "Toi qui disposes, de toutes choses \nEt nous les donnes chaque jour, \nReçois, ô Père! Notre prière \nDe reconnaissance et d’amour!",
                "Le don suprême, que Ta main sème \nC’est Ton pardon, oui c’est Ta paix. \nEt Ta clémence, trésor immense, \nEst le plus grand de Tes bienfaits.",
                "Que par Ta grâce, l’instant qui passe \nServe à nous rapprocher de Toi! \nEt qu’à chaque heure, vers Ta demeure \nNos cœurs s’élèvent par la foi!"
            ]
        },
        {
            "songTitle": "QUEL AMI FIDÈLE ET TENDRE",
            "id": 40,
            "songId": 7,
            "chorus": "",
            "key": "Fa majeur",
            "author": "J. M. Scriven(1855) C. C.Converse, Émile Bonnard",
            "enLyrics": [
                "Quel ami fidèle et tendre, \nNous avons en Jésus-Christ, \nToujours prêt à nous entendre, \nÀ répondre à notre cri! \nIl connaît nos défaillances, \nNos chutes de chaque jour. \nSévère en ses exigences, \nIl est riche en son amour.",
                "Quel ami fidèle et tendre, \nNous avons en Jésus-Christ, \nToujours prêt à nous comprendre, \nQuand nous sommes en souci! \nDisons-lui toutes nos craintes, \nOuvrons-lui tout notre cœur, \nBientôt ses paroles saintes, \nNous rendront le vrai bonheur.",
                "Quel ami fidèle et tendre, \nNous avons en Jésus-Christ, \nToujours prêt à nous défendre, \nQuand nous presse l’ennemi! \nIl nous suit dans la mêlée, \nNous entoure de ses bras, \nEt c’est lui qui tient l’épée, \nQui décide des combats.",
                "Quel ami fidèle et tendre, \nNous avons en Jésus-Christ, \nToujours prêt à nous apprendre, \nÀ vaincre en comptant sur lui! \nS’Il nous voit vrais et sincères, \nÀ chercher la sainteté, \nIl écoute nos prières, \nEt nous met en liberté.",
                "Quel ami fidèle et tendre, \nNous avons en Jésus-Christ, \nBientôt Il viendra nous prendre, \nPour être au ciel avec lui. \nSuivons donc l’étroite voie, \nEn comptant sur son secours. \nBientôt nous aurons la joie, \nDe vivre avec lui toujours!"
            ]
        },
        {
            "songTitle": "JESUS EST MON DIVIN BERGER",
            "id": 420,
            "songId": 8,
            "chorus": "",
            "key": "Fa majeur",
            "author": "F. H. Barthelemon, R. Simpson (1833), J. S. Irvine",
            "enLyrics": [
                "Jésus est mon divin Berger, \nRéjouis-toi mon âme. \nSeul Il délivre du danger, \nTout en moi le réclame.",
                "Non je ne manquerai de rien, \nCar ô grâce infinie. \nJésus est l'Ami, le gardien, \nEn qui je me confie.",
                "Jour après jour, Il me conduit \nDans ses verts pâturages. \nDe son Amour, Il me nourrit \nSous ses divins ombrages.",
                "Je ne craindrai donc aucun mal \nQuant au bout du voyage. \nIl me faudra du sombre val \nFranchir le noir passage.",
                "Toujours sa grâce et son amour \nMe suivront sur la terre. \nMais tout sera dans son séjour \nPaix, gloire, Amour, lumière."
            ]
        },
        {
            "songTitle": "SAUVEUR ADORABLE",
            "id": 71,
            "songId": 9,
            "chorus": "En toi je me cache, rocher de ma foi, \nDans un pays assoiffé et aride. \nEn toi je me cache, Et ta grâce, ton amour \nRassasient mon âme avide. (bis)",
            "key": "Do majeur",
            "author": "Fanny Crosby (1890), William James Kirkpatrick (1890)",
            "enLyrics": [
                "Sauveur adorable, ô Jésus mon Roi, \nMon Dieu plein d’amour, plein de grâce, \nEn toi je me cache rocher de ma foi, \nCherchant le secours de ta face.",
                "Sauveur adorable, ô Jésus mon Roi, \nTu ôtes mes fardeaux et chaînes. \nTon Esprit me soutient, \nEt Il guide’ mes pas. \nTa tendresse’ soulage ma peine.",
                "Rempli de ta bonté, ô vie de bonheur, \nQui déborde de tes richesses! \nJe chante alléluia! Gloire au Seigneur! \nEt loue mon Sauveur sans cesse.",
                "Quand Il reviendra, \nJ’entendrai son appel, \nEt irai vers lui dans les nuages. \nQuel bonheur il y aura avec lui au ciel! \nRegardant toujours son visage."
            ]
        },
        {
            "songTitle": "DIVIN ROCHER REFUGE SÛR",
            "id": 64,
            "songId": 10,
            "chorus": "Oui Jésus est le Roc dans un pays troublé, \nUn pays troublé, un pays troublé. \nJésus-Christ est le Roc dans un pays troublé: \nL’abri pour nous dans la tempête!",
            "key": "Fa majeur",
            "author": "V. J. Charlesworth, (1880) D. Sankey (1880)",
            "enLyrics": [
                "Divin Rocher, Refuge sûr: \nL’abri pour nous dans la tempête! \nNotre défense en combat dur: \nL’abri pour nous dans la tempête!",
                "Une ombre au jour un mur la nuit: \nL’abri pour nous dans la tempête! \nNulle peur donc de l’ennemi: \nL’abri pour nous dans la tempête!",
                "Si l’orage éclate alentour: \nL’abri pour nous dans la tempête! \nNous restons forts par Son secours: \nL’abri pour nous dans la tempête!",
                "Divin Rocher, Refuge aimé: \nL’abri pour nous dans la tempête! \nSois notre aide à tout jamais: \nL’abri pour nous dans la tempête!"
            ]
        },
        {
            "songTitle": "MON JÉSUS, JE T’AIME ",
            "id": 57,
            "songId": 11,
            "chorus": "",
            "key": "Fa majeur",
            "author": "W.R. Featherston (1864), A. J. Gordon(1894), G. Isely(1914)",
            "enLyrics": [
                "Mon Jésus, je t’aime, je te sais à moi. \nOh, quel charme extrême me retient à toi! \nLes plaisirs du monde, ne m’attirent plus, \nTon amour m’inonde, je t’aime, ô Jésus!",
                "Mon Jésus, je t’aime, car tu m’as sauvé \nEn T’offrant toi-même, ton sang m’a lavé! \nSur la croix infâme, pour moi, tu mourus. \nTa mort est ma vie, je t’aime, ô Jésus!",
                "Qu’ici-bas je t’aime, jusque dans la mort, \nÀ l’heure suprême, du dernier effort, \nMa voix expirante, ne s’entendra plus, \nSachez que je chante: “Je t’aime, ô Jésus!”",
                "Je verrai ta face, quel ravissement! \nJe louerai ta grâce, éternellement \nEt dirai sans cesse, avec les élus \nL’hymne d’allégresse: “Je t’aime, ô Jésus!”"
            ]
        },
        {
            "songTitle": "ROI DE MA VIE",
            "id": 63,
            "songId": 12,
            "chorus": "Que jamais je n’oublie, ô Dieu, \nTon grand amour si merveilleux! \nGarde toujours devant mes yeux \nLe Christ mourant en croix!",
            "key": "Mi ♭ majeur",
            "author": "J. E.Hussey (1921), W. Kirkpatrick (1921)",
            "enLyrics": [
                "Roi de ma vie, reçois l’hommage, \nSois adoré, exalté! \nDe ma misère’, mon esclavage, \nMourant Tu m’as sauvé.",
                "Agonissant sur le calvaire, \nJe vois souffrir pour moi, \nBuvant la coupe’, si pleine, amère, \nToi, Sauveur, à la croix.",
                "Déposé dans un froid tombeau, \nAyant rendu Ton âme, \nTon corps brisé reçut le repos \nAprès une’ mort infâme.",
                "Sauveur, je te prie, aide-moi \nÀ suivre ton modèle, \nPortant à chaque instant ma croix, \nRestant toujours fidèle.",
                "Et chauffe en moi un feu vivant, \nAllumé au calvaire, \nPour annoncer aux cœurs errants \nTon amour salutaire."
            ]
        },
        {
            "songTitle": "Ô FILS DE DIEU",
            "id": 72,
            "songId": 13,
            "chorus": "",
            "key": "Fa majeur",
            "author": "Isaac Watts (1707), Lowell Mason (1824)",
            "enLyrics": [
                "Ô Fils de Dieu quand nous voyons, \nLa coupe qu’il te fallut boire, \nPour nous donner ta propre gloire, \nOui, d’un seul cœur nous te louons.",
                "Pour toi, Jésus, furent les pleurs, \nL’adversité, la mort cruelle. \nPour nous, c’est la vie éternelle, \nCe sont les célestes faveurs.",
                "Du monde eussions-nous tous les biens, \nTrop petite en serait l’offrande, \nEn raison de l’œuvre si grande \nQue rappellent ici les tiens.",
                "Maintenant donc, et pour jamais \nAutour de ta sainte personne, \nSeigneur Jésus, l’église entonne \nUn chant d’allégresse et de paix."
            ]
        },
        {
            "songTitle": "O L’AGNEAU DE DIEU SANGLANT,",
            "id": 421,
            "songId": 14,
            "chorus": "Lieu de grâce Golgotha, \nLieu de grâce Golgotha, \nOù mon Sauveur mourut pour moi : \nLieu de grâce Golgotha !",
            "key": "Fa majeur",
            "author": "Eliza E. Hewitt (1897)",
            "enLyrics": [
                "A la croix pour moi souffrant, \nTu mourus en honte, angoisse, \nPrenant au Calvaire ma place.",
                "Couronné d’épines pour moi, \nTon corps cloué sur le bois, \nJe te vois verser ton sang, \nSubissant mon châtiment.",
                "Quel amour riche, infinie, \nRemplissait toute ta vie. \nEn rançon pour me sauver \nTu viens pour te sacrifier.",
                "Jésus, pour ton sacrifice \nPrends ma vie et mon sacrifice ! \nQu’ils soient pour le Calvaire \nMa grâce et mon salaire."
            ]
        },
        {
            "songTitle": "PRÈS DU TRÔNE",
            "id": 73,
            "songId": 15,
            "chorus": "Viens, oh! Viens, viens avec moi, \nViens, oh! Viens, viens à la croix! \nÀ la croix viens et vois, \nViens cher ami, viens avec moi à la croix!",
            "key": "Do majeur",
            "author": "Auteur inconnu",
            "enLyrics": [
                "Près du trône de la grâce et de la paix, \nJ’ai reçu la promesse d’un Dieu parfait. \nEn Jésus j’ai la victoire \nPar Sa mort expiatoire, \nPrès du trône de la grâce et de la paix.",
                "Fuis le monde, vanité des vanités: \nPoint de paix pour l’âme en ses frivolités. \nPar lui satan nous opprime, \nNous conduisant à l’abîme. \nFuis le monde, vanité des vanités!",
                "Je veux être un vaillant soldat du Sauveur, \nLutter, combattre toujours avec ferveur. \nEt, rempli de confiance, \nJ’accepterai la souffrance. \nJe veux être un vaillant soldat du Sauveur.",
                "Quand devant moi s’ouvriront les portes d’or, \nEt qu’enfin j’atteindrai le céleste port, \nUn bonheur pur et sans ombre \nRemplacera la nuit sombre, \nQuand devant moi \nS’ouvriront les portes d’or."
            ]
        },
        {
            "songTitle": "SEIGNEUR, TA MORT",
            "id": 74,
            "songId": 16,
            "chorus": "Je t’aimerai sans cesse, \nMon Sauveur, mon Sauveur; \nJe t’aimerai sans cesse, \nPour tous Tes grands bienfaits.",
            "key": "Mi ♭ majeur",
            "author": "Charles Hutchinson Gabriel, 1890",
            "enLyrics": [
                "Seigneur, ta mort à Golgotha, \nMe fait t’aimer sans cesse. \nEt ne permet mon grand Roi, \nQue jamais je te laisse.",
                "Du châtiment de mes péchés, \nQui était mon mérite, \nTon sacrifice m’a sauvé \nDans ta plus forte lutte.",
                "Ton sang versé me purifie \nDe toutes mes souillures. \nTon corps brisé pour moi acquit \nPardon par Ses blessures.",
                "Y a-t-il comme toi un autre ami \nQui sans réserve m’aime, \nQui m’aide dans toute ma vie, \nDonnant ses biens suprêmes?",
                "Beaucoup peuvent t’abandonner, \nJe t’aimerai sans cesse. \nPour ton amour et ta bonté, \nÀ jamais je t’embrasse."
            ]
        },
        {
            "songTitle": "VENEZ AU SAUVEUR",
            "id": 6,
            "songId": 17,
            "chorus": "Oh ! quel beau jour, Sauveur fidèle, \nQuand, nous appuyant sur ton bras, \nDans la demeure paternelle \nNous porterons nos pas !",
            "key": "Si ♭ majeur",
            "author": "A.Glardon, George F. Root (1878)",
            "enLyrics": [
                "Venez au Sauveur qui vous aime, \nVenez, Il a brisé vos fers ; \nIl veut vous recevoir Lui-même, \nSes bras vous sont ouverts.",
                "Venez, pécheurs, Il vous appelle, \nLe bonheur est dans son amour. \nAh ! donnez-lui ce cœur rebelle, \nDonnez-le sans retour.",
                "Le temps s'enfuit, l'heure s'écoule, \nQui sait si nous vivrons demain ? \nJésus est ici dans la foule ; \nAh! saisissez sa main !"
            ]
        },
        {
            "songTitle": "PUBLIEZ BIEN HAUT",
            "id": 75,
            "songId": 18,
            "chorus": "Le salut pour tous, le salut par grâce, \nÀ tous est offert, à tous est donné. \nOh! Venez, pécheurs, \nVenez, le temps passe, \nEt vous serez pardonnés.",
            "key": "Do majeur",
            "author": "A. Glardon, P. P. Bliss (1870)",
            "enLyrics": [
                "Publiez bien haut la grande nouvelle: \nLe ciel est ouvert à tout être humain. \nLa route est tracée, un guide fidèle \nVous conduira par la main.",
                "Publiez bien haut la grande nouvelle: \nLe sang de Jésus a tout effacé. \nOù que vous soyez, \nC’est vous qu’Il appelle, \nVous qui L’avez offensé.",
                "Publiez bien haut la grande nouvelle: \nAu loin comme au près, faites-la courir, \nPartout où se trouve une âme rebelle, \nUn pécheur à secourir."
            ]
        },
        {
            "songTitle": "ENTENDS-TU? JESUS T’APPELLE ",
            "id": 76,
            "songId": 19,
            "chorus": "Laisse entrer le Roi de gloire, \nOuvre ton cœur à Jésus! \nLaisse entrer le Roi de gloire, \nHâte-toi ne tarde plus.",
            "key": "Do majeur",
            "author": "A.Humbert, C. C. Williams (1871)",
            "enLyrics": [
                "Entends-tu? Jésus t’appelle. \nViens, ô pécheur! Il t’attend. \nÀ cette voix si fidèle \nTu résistas trop souvent.",
                "Pour le péché, pour le monde, \nTu trouves place en ton cœur, \nPoint pour le Sauveur du monde, \nRien pour l’homme de douleur!",
                "Jésus frappe, Il frappe encore. \nOuvre à ton Libérateur, \nEt pour toi luira l’aurore \nDu véritable bonheur.",
                "Aujourd’hui, c’est jour de grâce. \nNe compte pas sur demain. \nPendant que ton Sauveur passe, \nSaisis Sa puissante main!"
            ]
        },
        {
            "songTitle": "POURQUOI DONC ATTENDRE",
            "id": 422,
            "songId": 20,
            "chorus": "Pourquoi ? Pourquoi ? \nNe viens-tu pas aujourd’hui ? \nPourquoi ? Pourquoi ? \nNe veux-tu donc pas de Lui ?",
            "key": "La majeur",
            "author": "Alexandre Morel, George Frederick Root (1878)",
            "enLyrics": [
                "Pourquoi donc attendre mon frère ? \nTon Sauveur t'appelle aujourd'hui. \nLève-toi, sors de ta misère, \nIl t'aime, Il t'aime, viens à Lui.",
                "L'heure de ton salut s'envole \nMaintenant tu pourrais encore \nSaisir Jésus qui seul console. \nL'avoir, ce serait un trésor.",
                "Ne sens-tu pas au fond de ton âme \nLa puissance de l'Esprit-Saint ? \nNe veux-tu pas que de sa flamme \nJésus te vivifie enfin ?",
                "Pourquoi refuses-tu, mon frère, \nQuand la mort s'approche de toi ? \nTandis que brille la lumière, \nViens à Jésus, viens à la croix."
            ]
        },
        {
            "songTitle": "DOUCEMENT, TENDREMENT",
            "id": "77a",
            "songId": 21,
            "chorus": "Venez, venez à Moi! \nFatigués, chargés, venez à Moi! \nDoucement, tendrement \nJésus appelle, venez, \noh! Venez à Moi!",
            "key": "La ♭ / Sol majeur",
            "author": "Will L. Thompson (1880)",
            "enLyrics": [
                "Doucement, tendrement Jésus appelle, \nNous appelle, vous et moi; \nPatiemment Jésus attend le rebelle, \nIl nous attend, vous et moi!",
                "N’hésitons plus puisque \nle Sauveur plaide, \nPlaide pour vous et pour moi; \nPar des soupirs l’Esprit Saint intercède, \nEt c’est pour vous et pour moi.",
                "Le monde, hélas! \nN’est qu’une ombre qui passe, \nPasse pour vous et pour moi; \nGloire à Jésus! Au ciel est une place, \nPrête pour vous et pour moi.",
                "Au vrai bonheur, \nJésus-Christ nous convie, \nBonheur pour vous et pour moi; \nIl nous l’acquit quand Il donna Sa vie, \nSa vie est pour vous et moi."
            ]
        },
        {
            "songTitle": "CŒURS FATIGUES ET LASSES DU PECHE",
            "id": 423,
            "songId": 22,
            "chorus": "venez à lui, venez à lui ; \nVenez à Jésus, \nVenez à Jésus aujourd’hui!",
            "key": "DO majeur",
            "author": "F. J. Crosby (1820-1915), G. C. Stebbins, (1846-1945)",
            "enLyrics": [
                "Cœurs fatigués et lassés du péché, \nAssez souffert! Assez cherché ! \nJe puis donner la paix et le repos, \nMe charger de vos fardeaux.",
                "Vous tous, pécheurs condamnés par la loi, \nVenez à moi ! venez à moi ! \nVous recevrez en vos cœurs dès ce jour \nLe pardon du Dieu d’amour.",
                "Vous souffrez, par le mal asservis, \nSoyez par moi tous affranchis, \nOh ! venez tous, travaillés et chargés, \nEt vous serez soulagés."
            ]
        },
        {
            "songTitle": "DIS, SAIS-TU QUE JESUS-CHRIST SEUL PURIFI?",
            "id": 424,
            "songId": 23,
            "chorus": "Oh ! veux-tu, oh ! veux-tu \nQue son sang coule sur ton cœur ? \nSeul il peut ôter du péché la souillure, \nDe la neige donner la blancheur.",
            "key": "La ♭ majeur",
            "author": "E. A. Hoffman (1878)",
            "enLyrics": [
                "Es-tu lavé dans le sang de l’Agneau ? \nAs-tu confiance en sa grâce infinie \nEs-tu lavé dans le sang de l’Agneau ?",
                "Habites-tu chaque jour en sa présence ? \nEs-tu lavé dans le sang de l’Agneau ? \nConnais-tu de notre Sauveur la \npuissance ? \nEs-tu lavé dans le Sang de l’Agneau ?",
                "Tes vêtements sont-ils purs pour sa \nvenue ? \nEs-tu lavé dans le sang de l’Agneau ? \nAux cieux ton âme sera-elle reçue ? \nEs-tu lavé dans le sang de l’Agneau ?"
            ]
        },
        {
            "songTitle": "VEUX-TU BRISER",
            "id": 13,
            "songId": 24,
            "chorus": "Je suis fort, fort! Oui, \nplus que vainqueur, \nPar le sang de Jésus! \nJe suis fort, fort! \nOui, plus que vainqueur, \nPar le sang de Jésus mon Sauveur!",
            "key": "Mi majeur",
            "author": "G. Guillod, Lewis E. Jones (1899)",
            "enLyrics": [
                "Veux-tu briser du péché le pouvoir? \nLa force est en Christ! \nLa force est en Christ! \nSi dans ton cœur tu veux Le recevoir: \nLa force est dans le sang de Christ!",
                "Veux-tu braver et la mort et l’enfer? \nLa force est en Christ! \nLa force est en Christ! \nJésus, d’un mot \nFait tomber tous tes fers: \nLa force est dans le sang de Christ.",
                "Veux-tu marcher \nToujours pur, triomphant? \nLa force est en Christ! \nLa force est en Christ! \nPour te garder, \nJésus est tout-puissant: \nLa force est dans le sang de Christ!",
                "Veux-tu du ciel \nT’approcher chaque jour? \nLa force est en Christ! \nLa force est en Christ! \nAvec Jésus demeurer pour toujours: \nLa force est dans le sang de Christ!"
            ]
        },
        {
            "songTitle": "SOURCE DE GRACE",
            "id": 425,
            "songId": 25,
            "chorus": "Oui, je puis croire, Oui, je veux croire \nQue Jésus-Christ est mort pour moi! \nSa mort sanglante et triomphante \nMe rend libre par la foi.",
            "key": "Sol majeur",
            "author": "Luc Pulsford, Mélodie anglaise (19ème Siècle)",
            "enLyrics": [
                "Source de grace source efficace \nQui du mont Golgotha jaillit ! \nLa mort subie par Christ, la vie, \nNous dit : ״Tout est accompli״!",
                "Source de vie : nos maladies \nJésus nous en a délivrés ! \nJe sens renaître dans tout mon être \nLa vigueur et la santé.",
                "Jésus envoie l’Esprit de joie \nDans les cœurs lavés par le sang: \nL’Esprit de gloire et de victoire \nSur les rachetés descend !",
                "Pour récompense de ses souffrances, \nDevant sont trône Jésus voit \nLa sainte église qu’il s’est acquise \nAu prix du sang de la croix."
            ]
        },
        {
            "songTitle": "A LA CROIX OU MOURUT",
            "id": 7,
            "songId": 26,
            "chorus": "",
            "key": "Sol majeur",
            "author": "Elisha A. Hoffman in (1878)",
            "enLyrics": [
                "À la croix où mourut mon Sauveur, \nJe suis venu, brisé de douleur ; \nLà son sang purifia mon cœur. \nÀ son nom la gloire ! \nÀ son nom la gloire ! \nLà son sang purifia mon cœur. \nÀ son nom la gloire !",
                "Quelle merveille ! Il vint me sauver ; \nQuand de sa croix je me fus chargé, \nEn moi Jésus vint pour demeurer. \nÀ son nom la gloire ! \nÀ son nom la gloire ! \nEn moi Jésus vint pour demeurer. \nÀ son nom la gloire !",
                "Ô fontaine effaçant le péché, \nDonnant la vie au cœur desséché ! \nLà, Jésus me retient attaché. \nÀ son nom la gloire ! \nÀ son nom la gloire ! \nÀ son nom la gloire ! \nLà, Jésus me retient attaché. \nÀ son nom la gloire !",
                "Pauvre âme, viens aux pieds du Sauveur, \nÀ la source ouverte à tout pécheur ; \nViens t’y plonger, trouver le bonheur. \nÀ son nom la gloire ! \nÀ son nom la gloire ! \nViens t’y plonger, trouver le bonheur. \nÀ son nom la gloire !"
            ]
        },
        {
            "songTitle": "SUR LA PLACE DU VILLAGE",
            "id": 78,
            "songId": 27,
            "chorus": "Seigneur, doux Maître! \nEn Toi seul j’ai foi. \nDaigne restaurer mon être. \nSeigneur, guéris-moi!",
            "key": "Sol majeur",
            "author": "Music. W. Howard Doane (1870)",
            "enLyrics": [
                "Sur la place du village, \nIls sont accourus, \nLes malheureux de tout âge, \nCriant à Jésus:",
                "Qu’il vous soit fait, dit le Maître, \nSelon votre foi. \nSa parole les pénètre, \nBannit leur effroi.",
                "Il pose Ses mains bénies, \nSur leurs fronts brûlants \nEt chasse la maladie \nDe leurs corps souffrants.",
                "Et soudain la vie divine, \nRestaure leurs corps. \nComme hier en Palestine, \nIl guérit encore."
            ]
        },
        {
            "songTitle": "SEIGNEUR, À TON APPEL",
            "id": 79,
            "songId": 28,
            "chorus": "",
            "key": "",
            "author": "Ray Palmer (1830), L. Mason (1832)",
            "enLyrics": [
                "Seigneur, à Ton appel, \nÀ l’ordre universel de l’Éternel, \nNous voici pour la guerre, \nSur nos cous, notre Père, \nBrise de l’adversaire le joug cruel.",
                "Tu brisas nos liens; \nÀ Toi nos corps, nos biens, \nNous sommes Tiens! \nNous voici, cœur et vie, \nToute une armée unie \nQui combat et qui prie; Tu la soutiens!",
                "Nous voulons, Rédempteur, \nAnnoncer au pécheur le seul Sauveur; \nOffrir Ta grâce au pire, \npuis sous Ton Saint empire \nQu’il lutte et qu’il expire, triomphateur!",
                "Sauveur, divin Modèle, \nÀ Tes pieds demeurer, Guide fidèle, \nConduis-moi tendre Père, \nA Toi seul je veux être, \nEt vivre toute ma vie pour Toi, doux Maître."
            ]
        },
        {
            "songTitle": "J’ENTENDS TA DOUCE VOIX",
            "id": 26,
            "songId": 29,
            "chorus": "",
            "key": "Ré majeur",
            "author": "G. Reganey, Lewis Hartsough (1872)",
            "enLyrics": [
                "J’entends Ta douce voix, \nJésus, je viens à Toi. \nJe viens, ô Sauveur, lave moi \nDans le sang de Ta croix! \nJésus, Roi des rois, \nQui mourut pour moi, \nJe veux mourir avec Toi, \nAvec Toi sur la croix.",
                "J’entends Ta douce voix, \nQui me dit: “Crois en Moi!” \nJe crois, Seigneur, soutiens ma foi, \nTiens-moi près de Ta croix!",
                "J’entends Ta douce voix, \nElle pénètre en moi, \nEt me dit d’aimer comme Toi, \nDe l’amour de la croix!"
            ]
        },
        {
            "songTitle": "LONGTEMPS J’ERRAIS LOIN DE TOI,",
            "id": 426,
            "songId": 30,
            "chorus": "Je reviens, je reviens, \nPour ne plus errer \nJe reviens, je reviens, \nJe reviens, mon Dieu.",
            "key": "La ♭ majeur",
            "author": "William J. Kirkpatrick (1892)",
            "enLyrics": [
                "Je reviens, mon Père. \nJ’aimais le monde et le péché ; \nJe reviens, mon Père.",
                "J’ai gaspillé de longues années ; \nJe reviens, mon Père. \nReçois mon cœur contrit, brisé ; \nJe reviens, mon Père.",
                "Oui, fatigué de mes péchés \nJe reviens, mon Père. \nA toi je veux m’abandonner. \nJe reviens, mon Père.",
                "Le cœur blessé, l’esprit souffrant, \nJe reviens, mon Père. \n״Pardonne-moi le patient !״ \nJe reviens, mon Père."
            ]
        },
        {
            "songTitle": "TEL QUE JE SUIS",
            "id": 11,
            "songId": 31,
            "chorus": "",
            "key": "Mi ♭ majeur",
            "author": "Charlotte Elliott (1835)",
            "enLyrics": [
                "Tel que je suis, sans rien à moi, \nSinon Ton sang versé pour moi; \nEt Ta voix qui m’appelle à Toi, \nAgneau de Dieu, je viens, je viens!",
                "Tel que je suis, bien vacillant, \nEn proie au doute à chaque instant, \nLutte au dehors, crainte au dedans, \nAgneau de Dieu, je viens, je viens!",
                "Tel que je suis, Ton cœur est prêt \nÀ prendre le mien tel qu’il est. \nPour tout changer, Sauveur parfait! \nAgneau de Dieu, je viens, je viens!",
                "Tel que je suis, Ton grand amour \nA tout pardonné sans retour. \nJe veux être à Toi dès ce jour; \nAgneau de Dieu, je viens, je viens!"
            ]
        },
        {
            "songTitle": "AU PIED DE LA CROIX SANGLANTE",
            "id": 22,
            "songId": 32,
            "chorus": "Le parfait bonheur, \nLe parfait bonheur, \nC'est de mettre tout mon être \nA tes pieds, Seigneur !",
            "key": "Ré majeur",
            "author": "E.-L. Budry (1854-1932), W.-S. Weeden (1847-1908)",
            "enLyrics": [
                "Au pied de la croix sanglante, \nOù tu t'es donné pour moi, \nMon âme émue et tremblante, \nO Jésus se livre à Toi.",
                "Me voici pour ton service, \nJe ne garde rien pour moi, \nSur l'autel du sacrifice \nJe me place par la foi.",
                "Prends, Seigneur, ma vie entière, \nMets sur moi ton divin sceau ; \nFais d'un fils de la poussière, \nUn enfant du Dieu très-haut.",
                "A la gloire, aux biens du monde, \nJe renonce pour jamais ; \nQue le Saint-Esprit m'inonde \nDe ta joie et de ta paix !",
                "Si ma faiblesse est bien grande, \nTa force est plus grande encore, \nO Jésus, qu'elle me rende \nFidèle jusqu'à la mort !",
                "O félicité suprême ! \nTa grâce est mon bouclier. \nEt je t'appartiens, je t'aime, \nToi qui m'aimas le premier."
            ]
        },
        {
            "songTitle": "JÉSUS DOUX MAÎTRE",
            "id": 80,
            "songId": 33,
            "chorus": "",
            "key": "Mi ♭ majeur",
            "author": "Adelaide A. Pollard (1902) , George C. Stebbins (1907)",
            "enLyrics": [
                "Jésus, doux Maître, \nRègne sur moi, \nSoumets mon être, \nSois en le Roi. \nJe suis l’argile, toi, le Potier, \nRends-moi docile, ton prisonnier.",
                "Jésus, Lumière, pénètre en moi, \nÉprouve, éclaire ma faible foi; \nPlus blanc que neige, \nRends-moi, Seigneur, \nEt de tout piège, \nGarde mon cœur.",
                "Ô Jésus source de guérison, \nSois dans ma course, santé, pardon! \nPar Ta puissance protège-moi! \nPar Ta présence révèle-Toi!",
                "Je m’abandonne, Jésus à Toi; \nDétruis, pardonne tout mal en moi. \nRemplis mon âme de Ton Esprit, \nEt qu’Il m’enflamme et jour et nuit!"
            ]
        },
        {
            "songTitle": "Ô VOUS QUI N’AVEZ PAS LA PAIX",
            "id": 4,
            "songId": 34,
            "chorus": "Quand Jésus remplit un cœur, \nIl déborde de bonheur, \nEt l’effroi ne l’atteint plus, \nGloire, gloire à Jésus!",
            "key": "Ré majeur",
            "author": "William Howard Doane, Mlle N. Coulin (1911)",
            "enLyrics": [
                "Ô vous qui n’avez pas la paix, \nVenez, Jésus la donne. \nPure, profonde et pour jamais: \nVenez, Jésus pardonne.",
                "Vous qui tombez à chaque pas, \nVenez, Jésus délivre; \nCelui qui se jette en Ses bras, \nPeut à toujours Le suivre. \nQuand Jésus remplit un cœur, \nIl déborde de bonheur, \nCar il ne chancelle plus, \nGloire, gloire à Jésus!",
                "Vous qui craignez le lendemain, \nVenez : Jésus rassure ; \nPas à pas, la main dans sa main, \nLa route devient sûre. \nQuand Jésus remplit un cœur, Il \nDéborde de bonheur, \nEt l’effroi ne l’atteint plus, \nGloire, gloire à Jésus !",
                "Vous qui tremblez sous la terreur \nQue la mort vous inspire, \nVenez, votre Libérateur, \na détruit son empire! \nAvec Lui nous revivrons, \nAvec Lui nous régnerons, \nEt la mort ne sera plus: \nGloire, gloire à Jésus!"
            ]
        },
        {
            "songTitle": "JE SUIS JEUNE ET DELIVRE",
            "id": 427,
            "songId": 35,
            "chorus": "Oui, d’être jeune, \nC’est merveilleux \nC’est mieux encor d’être sauvé ; \nPourtant, voici le mieux de tout : \nJeune et sauvé de tous péchés,",
            "key": "Fa majeur",
            "author": "Auteur Inconnu",
            "enLyrics": [
                "Du fardeau de mes péchés. \nMaintenant je suis fort et heureux, \nMarchant avec l’Eternel \nParmi ceux qui vont au ciel, \nVers la sainte demeure de Dieu.",
                "Je suis jeune et bien content \nDe servir par le talent \nQue la grâce de Dieu m’a donné. \nTous sont appelés de Dieu \nA mener les malheureux \nVers Jésus le Sauveur des perdus.",
                "Je suis jeune et toi aussi : \nEcoute mon chant ici ; \nNe désires-tu pas le bonheur ? \nDieu t’appel à son salut, \nViens reçois-le par Jésus, \nSois heureux comme moi \nDans ton cœur."
            ]
        },
        {
            "songTitle": "ROC SECULAIRE",
            "id": 12,
            "songId": 36,
            "chorus": "Roc séculaire, frappé pour moi \nSur le Calvaire, je viens à Toi. (bis)",
            "key": "Ré ♭ majeur",
            "author": "Augustus M. Toplady, (1891)",
            "enLyrics": [
                "Roc séculaire, frappé pour moi \nSur le Calvaire, je viens à Toi. \nTu sais mes chutes, ô mon Sauveur! \nTu vois mes luttes et ma douleur.",
                "Oh! Purifie, lave, Seigneur, \nEt sanctifie mon pauvre cœur. \nMa main tremblante ne T’offre rien; \nTa croix sanglante est mon seul bien.",
                "Dans la détresse sois mon Berger, \nMa forteresse, dans le danger, \nEt qu’à toute heure, que chaque jour \nMon cœur demeure en Ton amour."
            ]
        },
        {
            "songTitle": "Ô JOUR HEUREUX",
            "id": 65,
            "songId": 37,
            "chorus": "Quel beau jour! Quel beau jour! \nOù d’un Sauveur j’ai su l’amour. \nOui, dans ma nouvelle patrie, \nJésus m’attend et pour moi prie. \nQuel beau jour! Quel beau jour! \nOù d’un Sauveur j’ai su l’amour.",
            "key": "Fa / Sol majeur",
            "author": "Philip Doddridge (1755), Ed. F. Rimbault, (1875)",
            "enLyrics": [
                "Ô jour heureux, jour de bonheur, \nLumière, paix, joie ineffable! \nAu Fils de Dieu, saint, adorable, \nÀ Jésus j’ai donné mon cœur.",
                "Oh! Comprenez mon heureux sort: \nC’est en Jésus que Dieu pardonne; \nLa vie éternelle Il la donne; \nPourquoi donc te craindrais-je, ô mort?",
                "Au ciel des chants ont retenti: \nAlléluia! Disent les anges, \nEntonnant de saintes louanges, \nCar un pécheur s’est converti.",
                "C’en est fait, tout est accompli, \nLe Fils de Dieu m’appelle frère; \nSon sang coula sur le Calvaire; \nIl est à moi et je suis à Lui."
            ]
        },
        {
            "songTitle": "QUELLE COMMUNION",
            "id": 81,
            "songId": 38,
            "chorus": "Gardé, gardé \nDe toute alarme de l’ennemi! \nGardé, gardé, \nGardé dans les bras \nPuissants de l’Éternel!",
            "key": "Sol majeur",
            "author": "E. A. Hoffman (1887) , A. J. Showalter(1887)",
            "enLyrics": [
                "Quelle communion! Quelle joie profonde! \nDans les bras puissants de l’Éternel. \nQuel repos céleste! Quelle paix abonde! \nDans les bras puissants de l’Éternel.",
                "Quelle sûreté dans chaque menace! \nDans les bras puissants de l’Éternel! \nQuelle victoire, par Sa pleine grâce, \nDans les bras puissants de l’Éternel.",
                "Que craindrais-je donc, \nsur mon chemin de vie, \nDans les bras puissants de l’Éternel. \nTous mes besoins sont en Lui remplis, \nDans les bras puissants de l’Éternel."
            ]
        },
        {
            "songTitle": "DAVANTAGE DE JESUS-CHRIST !",
            "id": 428,
            "songId": 39,
            "chorus": "Oui, davantage de Christ ! \nOui, davantage de Christ ! \nDavantage de son salut, \nDavantage de son Esprit !",
            "key": "Sol majeur",
            "author": "E. E. Hewitt (1887), John R. Sweney, pub.1887)",
            "enLyrics": [
                "Davantage dans toute ma vie ! \nDavantage de son salut, \nDavantage de son esprit !",
                "Davantage enseigne-moi, \nParole sainte, sur ses voies ! \nFais-montrer sa sainteté \nEt discerne sa volonté ! ",
                "Davantage dans la prière \nJ’aime connaître le mystère \nD’une union parfaite, constante \nEt d’une vie toujours triomphante.",
                "Davantage de Christ encore \nQuand j’entre dans la cité d’or ! \nQuelle richesse, quel héritage \nSeront à jamais mon partage !"
            ]
        },
        {
            "songTitle": "MON DIEU PLUS PRÈS DE TOI",
            "id": 43,
            "songId": 40,
            "chorus": "",
            "key": "Fa majeur",
            "author": "Charles Châtelanat, (1885)",
            "enLyrics": [
                "Mon Dieu plus près de toi, \nPlus près de toi! \nC’est le cri de ma foi: \nPlus près de toi! \nDans le jour où l’épreuve \nDéborde comme un fleuve, \nGarde-moi près de toi, \nPlus près de toi!",
                "Plus près de Toi, Seigneur, \nPlus près de Toi! \nTiens-moi dans ma douleur, \nPlus près de Toi! \nAlors que la souffrance, \nFait son œuvre en silence, \nToujours plus près de toi, \nSeigneur tiens-moi!",
                "Plus près de toi, \nToujours, plus près de toi! \nDonne-moi Ton secours, \nSoutiens ma foi! \nQue satan se déchaîne, \nTon amour me ramène \nToujours plus près de toi, \nplus près de toi!",
                "Mon Dieu plus près de toi, \nDans le désert, \nJ’ai vu, plus près de Toi, \nTon ciel ouvert. \nPèlerin bon courage! \nTon chant brave l’orage... \nMon Dieu plus près de toi, \nPlus près de toi!",
                "Enfin en sûreté, près du Seigneur, \nJe vivrai sans péché, \nDans le bonheur. \nD’âge en âge, tiens-moi, \nSeigneur plus près de toi. \nToujours plus près de toi, \nPlus près de toi!"
            ]
        },
        {
            "songTitle": "SEIGNEUR ATTIRE",
            "id": 54,
            "songId": 41,
            "chorus": "",
            "key": "Ré ♭ majeur",
            "author": "M. Hunter, Lelia Morris, (1898)",
            "enLyrics": [
                "Seigneur, attire mon cœur à toi, \nJe te désire, tout près de moi. \nMa délivrance, dans le danger, \nC’est ta présence, divin Berger. (x2)",
                "Par ta puissance, brise, soumets \nMa résistance à tout jamais. \nCourbe mon être, ma volonté, \nSois-en le Maître incontesté. (x2)",
                "Quand je contemple, près de ta croix, \nTon grand exemple, Jésus, mon Roi, \nAh! Je n’aspire qu’à m’immoler, \nTant je désire te ressembler! (x2)",
                "Prompt, je m’élance pour t’obéir, \nPrompt, je m’avance pour te servir; \nMais, sous ton aile, loin du péché, \nSauveur fidèle, tiens-moi caché. (x2)"
            ]
        },
        {
            "songTitle": "AU PIED DE LA SAINTE CROIX,",
            "id": 96,
            "songId": 42,
            "chorus": "Sainte croix, sainte croix, \nPar toi j’ai la vie ; \nC’est dans le sang de la croix \nQue je me confie.",
            "key": "AU PIED DE LA SAINTE CROIX,",
            "author": "James Hunter, William H. Doane (1869)",
            "enLyrics": [
                "Au pied de la sainte croix, \nJaillit la fontaine \nDu salut que je reçois, \nGrâce souveraine.",
                "Seigneur, le sang de ta croix \nMes péchés efface, \nTu me le dis, je le crois : \n« Du mal plus de trace. »",
                "Prosterné devant la croix \nSur le mont Calvaire,* \nDe Jésus je fais mon choix, \nEn lui seul j’espère.",
                "M’asseoir au pied de ta croix \nEst mon doux partage, \nC’est là que j’entends ta voix \nQui me dit : courage !"
            ]
        },
        {
            "songTitle": "JÉSUS-CHRIST EST MA SAGESSE",
            "id": 66,
            "songId": 43,
            "chorus": "",
            "key": "Fa / Sol majeur",
            "author": "Fanny Crosby (1874), Silas Jones Vail (1874)",
            "enLyrics": [
                "Jésus-Christ est ma sagesse, \nIl éclaire mon chemin, \nEt je marche, en ma faiblesse, \nConduit par Sa sûre main. \nIl éclaire mon chemin, (bis) \nEt je marche, en ma faiblesse, \nConduit par Sa sûre main.",
                "Jésus-Christ est ma justice; \nSon sang a coulé pour moi; \nJe trouve en Son sacrifice \nPaix et pardon par la foi. \nSon sang a coulé pour moi; (bis) \nJe trouve en Son sacrifice \nPaix et pardon par la foi.",
                "Jésus-Christ me sanctifie; \nAu divin Cep attaché, \nJe reçois de Toi la vie \nQui m’affranchit du péché. \nÀ Toi, Jésus, attaché, (bis) \nJe reçois de Toi la vie \nQui m’affranchit du péché."
            ]
        },
        {
            "songTitle": "J’AI SOIF DE TA PRÉSENCE",
            "id": 45,
            "songId": 44,
            "chorus": "Chaque jour, à chaque heure, \nOh! J’ai besoin de Toi. \nViens Jésus, et demeure \nAuprès de moi.",
            "key": "La ♭ majeur",
            "author": "A. Glardon (1839-1922), R. Lowry, A. S. Hawks (1872)",
            "enLyrics": [
                "J’ai soif de Ta présence, divin Chef de ma foi. \nDans ma faiblesse immense \nQue ferais-je sans Toi?",
                "Des ennemis, dans l’ombre, \nRôdent autour de moi. \nAccablé par le nombre, que ferais-je sans Toi?",
                "Pendant les jours d’orage, \nD’obscurité, d’effroi, \nQuand faiblit mon courage, \nque ferais-je sans Toi?",
                "Ô Jésus! Ta présence \nC’est la vie et la paix: \nLa paix dans la souffrance, \nEt la vie à jamais."
            ]
        },
        {
            "songTitle": "CROIRE, OBÉIR",
            "id": 61,
            "songId": 45,
            "chorus": "Croire, obéir: \nPour que Dieu puisse ouvrir \nLes écluses célestes, \nIl faut croire, obéir.",
            "key": "Fa majeur",
            "author": "John H. Sammis (1887), D. B. Towner (1887)",
            "enLyrics": [
                "Quand la Bible ici-bas, \nIllumine nos pas, \nDe sa gloire Dieu vient nous remplir. \nQuand je veux ce qu’Il veut, \nEn Son nom je le peux. \nSimplement il faut croire, obéir.",
                "Veux-tu la liberté, \nLe bonheur la santé? \nQue ton seul but soit de Le servir! \nCar l’Esprit n’est donné \nAvec la joie, la paix, \nQu’à celui qui veut croire, obéir.",
                "Les fardeaux, les labeurs, \nLe chagrin et les pleurs, \nÀ mon bien Dieu les fait concourir. \nIls deviendront au ciel \nDes trésors éternels. \nSimplement il faut croire, obéir.",
                "Nous pouvons dépasser \nNos incapacités, \nAux dessins éternels nous ouvrir : \nDe nouveaux horizons, \nUne vaste moisson… \nSimplement il faut croire, obéir.",
                "À Ses ordres soumis \nSans aucun compromis: \nAlors le Tout-Puissant peut agir. \nIl nous ouvre les flots, \nFait tomber Jéricho. \nSimplement il faut croire, obéir."
            ]
        },
        {
            "songTitle": "ENTENDS-TU LE CHANT ",
            "id": 82,
            "songId": 46,
            "chorus": "",
            "key": "Sol majeur",
            "author": "M. Hunter (1941), W. J. Kirkpatrick(1882)",
            "enLyrics": [
                "Entends-tu le chant joyeux? \nJésus sauve aujourd'hui! \nIl retendit en tout lieu, \nJésus sauve aujourd'hui! \nC'est un cri de délivrance, \nUn cantique d'espérance \nQui remplit l'espace immense, \nJésus sauve aujourd'hui!",
                "Partout élève la voix, \nJésus sauve aujourd'hui! \nVaillant Héraut de la croix, \nJésus sauve aujourd'hui! \nA parler Jésus t'appelle, \nRépands au loin la nouvelle, \nEn connais-tu de plus belle, \nJésus sauve aujourd'hui!",
                "Répète au pécheur contrit: \nJésus sauve aujourd'hui! \nCeux que le mal asservit, \nJésus sauve aujourd'hui! \nVa jusqu'à l'île lointaine \nBriser du captif la chaîne, \nRedire au coeur dans la peine, \nJésus sauve aujourd'hui!",
                "Jusqu'aux confins des déserts, \nJésus sauve aujourd'hui! \nJusque par-delà les mers, \nJésus sauve aujourd'hui! \nQue d'un pôle à l'autre pôle \nCoure la Sainte Parole \nQui relève, instruit, console, \nJésus sauve aujour'hui!"
            ]
        },
        {
            "songTitle": "ENTENDS-TU LE CRI SUR LA MER RUGISSANTE ?",
            "id": 429,
            "songId": 47,
            "chorus": "Fais briller à tous le feu : \nLe message du salut. \nFais briller à tous le feu \nPour sauver les naufragés !",
            "key": "Sol majeur",
            "author": "Chas. H. Gabriel (1890)",
            "enLyrics": [
                "״fait briller le port le feu !״ \nAux pécheurs perdus \nAnnonçons le salut ! \nFait briller du port le feu !",
                "Entends-tu l’appel \nMacédonéen ce jour ? \n״Fais briller du port le feu !״ \nMe voici, Seigneur !״ Réponds-tu à ton tour ? \nFais briller du port le feu !",
                "Que la grâce de Christ \nAtteigne le monde \nFais briller du port le feu ! \nSon Esprit donne la charité profonde. \nFais briller du port le feu !",
                "Ne nous fatiguons pas \nDans ce grand service! \nFais briller du port le feu ! \nDe sauver les naufragés soit la devise. \nFais brille du port le feu !"
            ]
        },
        {
            "songTitle": "LEVEZ LES YEUX SUR TOUT",
            "id": "83a",
            "songId": 48,
            "chorus": "Je suis avec vous tous les jours, \nComptez sur Mon puissant secours. \nAllez partout prêcher le saint Évangile, \nD’une ville à l’autre ville!",
            "key": "Sol majeur",
            "author": "James McGranahan (1887)",
            "enLyrics": [
                "Levez les yeux sur tout le vaste monde, \nVers les pays où règne encore la nuit, \nJésus attend que \nQuelqu’un lui réponde: \nSeigneur, j’irai, conduit par Ton Esprit.",
                "Levez les yeux car la moisson est mûre, \nPourquoi rester sans \nRien faire aujourd’hui? \nAvec Jésus, la tâche n’est point dure, \nN’hésitez plus. \nNe comptez que sur Lui!",
                "Levez les yeux, \nSonnez de la trompette, \nPour rallier sous l’étendard sanglant \nDe Jésus-Christ, \nTout héros, tout prophète, \nPrêt à mourir, s’il faut, en combattant!",
                "Levez les yeux sur \nL’immense détresse, \nDe tout mortel ignorant du salut. \nRéveillez-vous! Arrière la paresse! \nAllez! Partez! Courez droit vers le but!"
            ]
        },
        {
            "songTitle": "DEBOUT, SAINTE COHORTE",
            "id": 32,
            "songId": 49,
            "chorus": "",
            "key": "Fa majeur",
            "author": "Mélodie G.J. Webb(1858), parole R. Saillens (1878)",
            "enLyrics": [
                "Debout, sainte cohorte, \nSoldats du Roi des rois! \nTenez d’une main forte \nL’étendard de la croix! \nAu sentier de la gloire \nJésus-Christ vous conduit. \nDe victoire en victoire \nIl mène qui Le suit.",
                "La trompette résonne: \nDebout! Vaillants soldats! \nL’immortelle couronne \nEst le prix des combats. \nSi l’ennemi fait rage, \nSoyez fermes et forts! \nRedoublez de courage, \nS’il redouble d’efforts.",
                "Debout pour la bataille, \nPartez, n’hésitez plus! \nPour que nul ne défaille, \nRegardez à Jésus! \nDe l’armure invincible, \nSoldats, revêtez-vous! \nLe triomphe est possible \nPour qui lutte à genoux.",
                "Debout, debout encore! \nLuttez jusqu’au matin. \nDéjà brille l’aurore \nA l’horizon lointain. \nBientôt jetant nos armes \nAux pieds du Roi des rois! \nLes chants après les larmes, \nLe trône après la croix!"
            ]
        },
        {
            "songTitle": "DES QUE L’AUBE DEPOSE",
            "id": 430,
            "songId": 50,
            "chorus": "",
            "key": "Fa majeur",
            "author": "Anna L. Coghill (1854), Lowell Mason (1864)",
            "enLyrics": [
                "Ses perles sur les fleurs, \nDès que s’ouvre la rose \nAux brillantes couleurs, \nDès que l’ombre s’efface \nDevant le jour qui luit, \nA l’œuvre, le temps passe ! \nA l’œuvre avant la nuit !",
                "Quand le soleil inonde \nEt remplit le ciel bleu, \nIlluminant le monde \nDe ses rayons de feu, \nA l’œuvre sans relâche, \nA l’œuvre, le jour fuit ! \nSi pénible est la tâche \nBientôt viendra la nuit !",
                "A cette heure indécise, \nOù le jour disparaît, \nOù murmure la brise \nA travers la forêt, \nQuand le couchant se dore \nEt que s’éteint le bruit, \nFrère à l’œuvre encore, \nVoici, voici la nuit ! "
            ]
        },
        {
            "songTitle": "FRERES, EN AVANT",
            "id": 431,
            "songId": 51,
            "chorus": "Christ notre Roi. \nA toi nous rendons la gloire : \nChrist notre Roi, \nA toi appartient notre vie",
            "key": "Mi ♭ majeur",
            "author": "Auteur Inconnu",
            "enLyrics": [
                "Dans la sainte guerre ! \nSuivons l’étendard de la croix ! \nLuttons sans crainte ! \nNotre Chef demeure \nAvec nous dans chaque combat.",
                "Prenons les armes ! \nL’Esprit nous fortifie, \nNous fait triompher sur Satan. \n״toujours en avant ! \nJamais en arrière !״ \nVoilà la devise des vaillants.",
                "Christ nous dirige, \nJamais ne nous délaisse, \nMême dans le plus fort combat. \nDonc, nous le suivons, \nL’étendard ne se baisse, \nBientôt il sera Roi des rois."
            ]
        },
        {
            "songTitle": "LA LUTTE SUPRÊME",
            "id": 56,
            "songId": 52,
            "chorus": "Du Christ, la bannière \nSe déploie au vent. \nPour la sainte guerre, \nSoldats en avant!",
            "key": "Mi ♭ majeur",
            "author": "R. Saillens, A. Seymour Sullivan (1842-1900)",
            "enLyrics": [
                "La lutte suprême nous appelle tous, \nEt Jésus Lui-même marche devant nous. \nQue Sa vue enflamme \nTous Ses combattants \nEt soutienne l’âme des plus hésitants.",
                "L’ennemi redoute le nom seul du Roi.\nIl fuit en déroute au cri de la foi. \nAcclamons ensemble \nJésus d’un seul cœur, \nEt que l’enfer tremble \nA ce nom vainqueur.",
                "Nous suivons la trace \nDes saints d’autrefois: \nPar la même grâce, sous les mêmes lois. \nVivant de miracles, l’Église de Dieu, \nDe tous les obstacles, \nTriomphe en tout lieu.",
                "Que les ans s’écoulent, \nQue de toutes parts, \nÀ grand bruit s’écroulent \nTrônes et remparts: \nNotre citadelle, ferme contre tout, \nL’Église fidèle restera debout."
            ]
        },
        {
            "songTitle": "EN TON NOM, SAUVEUR DE GRACE,",
            "id": 432,
            "songId": 53,
            "chorus": "Que les portes des écluses \nMontent, nous prions, Seigneur ; \nQue l’Esprit nous tous inonde \nEt nous rend plus que vainqueurs.",
            "key": "La ♭ majeur",
            "author": "Mrs. C. H. Morris (19O8)",
            "enLyrics": [
                "Rassemblés en ce saint lieu \nNous cherchons ta sainte face \nDemandant tes dons, bon Dieu. \nDe ta plénitude immense \nEnvois-nous un grand réveil, \nDes torrents de délivrance \nDu péché et du sommeil.",
                "Que les portes des écluses \nS’ouvrent et ton grand salut \nSe répande sur l’Eglise, \nL’inondant en ton Esprit ; \nQue les morts et infidèles \nSe lèvent à ton appel, \nRecevant la vie nouvelle \nPar s’offrant sur ton autel. ",
                "Nous croyons, bientôt il viendra \nLe réveil que tu promis. \nA nos cris tu nous répondras \nPar la pluie de ton Esprit. \nTa gloire, ta puissance \nEn torrents vaste, infinis \nSe répandront en clémence, \nNous donnant ta sainte vie."
            ]
        },
        {
            "songTitle": "SEIGNEUR CE QUE MON CŒUR",
            "id": 84,
            "songId": 54,
            "chorus": "",
            "key": "Mi ♭ majeur",
            "author": "William Booth, (1894) Frederick Booth Tucker (1894)",
            "enLyrics": [
                "Seigneur ce que mon cœur réclame, \nC’est le feu. (x3) \nQue sur moi descende la flamme \nDe Ton feu. (x3) \nAinsi que dans la chambre haute, \nQu'une nouvelle Pentecôte \nFasse de nous de vrais apôtres, \nPleins de feu! (x3)",
                "Le seul secret de la victoire, \nC’est le feu! (x3) \nNous voulons refléter Ta gloire \nPar le feu! (x3) \nDieu Tout-Puissant, Toi qui nous aimes, \nViens nous affranchir de nous-mêmes. \nRemplis-nous d’un amour suprême, \nPar le feu! (x3)",
                "Nous voulons porter l’espérance, \nPar le feu! (x3) \nEt proclamer la délivrance, \nPar le feu! (x3) \nTon règne vienne sur la terre, \nTa volonté soit faite, ô Père. \nExauce enfin notre prière, \nPar le feu! (x3)"
            ]
        },
        {
            "songTitle": "UNIS DANS LA CHAMBRE HAUTE",
            "id": 433,
            "songId": 55,
            "chorus": "Seigneur, remplis-nous \nDe ton Esprit (ter) \nBaptise et sanctifie !",
            "key": "Fa majeur",
            "author": "Charles D. Tillman, (1895)",
            "enLyrics": [
                "Unis dans la chambre \nIls étaient en même accord \nQuand l’Esprit de Pentecôte \nDescendit comme un vent fort.",
                "Cette divine puissance \nRemplissait tous les cent-vingt \nLes rendit pleins de confiance \nEt pour Christ de vrais témoins.",
                "Oui, la promesse du Père \nFut remplie quand l’Esprit. \nEt en nos jours, sœurs et frères, \nDieu nous l’accorde aussi."
            ]
        },
        {
            "songTitle": "FRAÎCHES ROSÉES",
            "id": 14,
            "songId": 56,
            "chorus": "Fraîches rosées, \nDescendez sur nous tous! \nÔ divines ondées, \nVenez, arrosez-nous!",
            "key": "Si ♭ majeur",
            "author": "James McGranahan – Edmond Louis Budry (1907)",
            "enLyrics": [
                "Comme une terre altérée \nSoupire après l’eau du ciel, \nNous appelons la rosée \nDe Ta grâce, Emmanuel!",
                "Descends, ô pluie abondante, \nCoule à flots dans notre cœur, \nDonne à l’âme languissante \nUne nouvelle fraîcheur.",
                "Ne laisse en nous rien d’aride \nQui ne soit fertilisé, \nQue le cœur le plus avide \nSoit pleinement arrosé.",
                "Oui, que les déserts fleurissent \nSous Tes bienfaisantes eaux, \nQue les lieux secs reverdissent \nEt portent des fruits nouveaux."
            ]
        },
        {
            "songTitle": "RÉVEILLE-NOUS, SEIGNEUR",
            "id": 85,
            "songId": 57,
            "chorus": "Réveille-nous, Seigneur! \nPendant que nous prions \nDescends, Seigneur, descends vers nous! \nViens glorifier ton nom!",
            "key": "Fa majeur",
            "author": "Albert Midlane (1858), William Henry Walter (1894)",
            "enLyrics": [
                "Réveille-nous, Seigneur! \nFais montrer ta présence! \nÀ ta parole ouvre nos cœurs, \nEt parle avec puissance!",
                "Réveille-nous, Seigneur! \nPour exalter ton nom. \nMets ton amour dans chaque cœur, \nFais de nous des flambeaux.",
                "Réveille-nous, Seigneur! \nEt bénis ta parole. \nQue, par sa force et vérité, \nElle, nos vies contrôle.",
                "Réveille-nous, Seigneur! \nEnvoie ton Saint-Esprit. \nQu’Il nous remplisse de ferveur, \nDe chercher les perdus."
            ]
        },
        {
            "songTitle": "O PEUPLE FIDELE,",
            "id": 434,
            "songId": 58,
            "chorus": "Que votre amour l’implore, \nQue votre foi l’adore \nEt qu’elle chante encore \nCe don précieux ! (verset 1) \nSa gloire en ce jour ! (verset 2) \nSon règne sans fin ! (verset 3)",
            "key": "Fa majeur",
            "author": "J. F. Wade (1743); Recueil de la Conf. d'Augsbourg",
            "enLyrics": [
                "Jésus vous appelle, \nVenez triomphants, joyeux, \nVenez en ces lieux ! \nO peuple fidèle, \nVenez voir le Roi des cieux.",
                "Quoi ! dans l’humble étable, \nFroide et misérable, \nDes bergers le grand amour \nLui forme une cour ! \nDans cette humble étable \nAccourez à votre tour.",
                "C’est le Roi des anges, \nCaptifs dans les langes, \nSplendeur pure et sans déclin \nDu Père divin. \nC’est le Roi des anges, \nVoilé sous un corps humain."
            ]
        },
        {
            "songTitle": "VOICI NOEL, O DOUCE NUIT!",
            "id": 435,
            "songId": 59,
            "chorus": "",
            "key": "Si ♭ majeur",
            "author": "H. Mégroz-Cornaz, F. Grüber (1787-1863)",
            "enLyrics": [
                "L’étoile est là qui nous conduit. \nAllons tous avec les mages \nPorter à Jésus nos hommages \nCar l’enfant nous est né, \nLe Fils nous est donné !",
                "Voici noël oh ! quel beau jour ! \nJésus est né ! quel grand amour ! \nC’est pour nous qu’il vient sur la terre, \nQu’il prend sur lui notre misère. \nUn Sauveur nous est né, \nLe Fils nous est donné !",
                "Voici Noël ! ah ! d’un seul cœur \nJoignons nos voix au divin chœur \nQui proclame au ciel les louanges \nDe celui qu’annoncent les anges ! \nOui, l’enfant nous est né, \nLe Fils nous est donné !"
            ]
        },
        {
            "songTitle": "CHRIST EST RESSUSCITE",
            "id": 3,
            "songId": 60,
            "chorus": "À toi la gloire et l’honneur, \nÔ Sauveur, \nO puissant Rédempteur! \nDu sépulcre, \nTu sortis vainqueur, \nPrince de vie \nEt Prince de paix. \nGloire à toi! Gloire à toi! \nGloire à toi! Gloire à jamais!",
            "key": "Si ♭ majeur",
            "author": "",
            "enLyrics": [
                "Christ est ressuscité! \nQu’en des chants joyeux, \nSon triomphe en tous lieux \nSoit exalté.",
                "Christ est ressuscités! \nCherche en lui toujours, \nÔ peuple racheté, \nForce et secours!",
                "Christ est ressuscité! \nPar lui, nous vivrons \nEt dans l’éternité, \nNous règnerons."
            ]
        },
        {
            "songTitle": "BEAU PAYS DE LUMIÈRE",
            "id": "86a",
            "songId": 61,
            "chorus": "Oh! Quel doux rendez-vous, \nAprès notre terrestre voyage, \nOh! Quel doux rendez-vous, \nTon céleste repos est pour nous",
            "key": "Fa majeur",
            "author": "Bennett (1868) J.P. Webster (1868)",
            "enLyrics": [
                "Beau pays de lumière et d’amour, \nPar la foi nous voyons ton rivage. \nNos pensées s’arrêtent chaque jour, \nAux bien-aimés déjà sur la plage.",
                "Et le beau cantique de l’Agneau, \nNous le chanterons avec les anges, \nLe bonheur sera toujours nouveau, \nJamais ne cesseront les louanges.",
                "Oui, nous voulons bénir le Seigneur; \nLouer d’un cœur joyeux notre Père, \nDont l’amour nous donna pour Sauveur, \nJésus-Christ qui Se fit notre Frère."
            ]
        },
        {
            "songTitle": "QUAND LA TROMPETTE",
            "id": 87,
            "songId": 62,
            "chorus": "À l’appel de la trompette, (x3) \nQuand Jésus-Christ reviendra \nJe serai prêt.",
            "key": "La ♭ majeur",
            "author": "Knowles Shaw (1874), James M. Black (1893)",
            "enLyrics": [
                "Quand la trompette céleste \nAnnoncera les temps nouveaux, \nQuand poindra l’aurore de l’éternité, \nEt que s’ouvrira le grand \nLivre de vie de l’Agneau, \nPourrons-nous répondre \nÀ l’appel: “Je suis prêt”?",
                "Oh! Quel glorieux réveil: \nLes morts en Christ se lèveront, \nEt nous qui serons vivants, \nserons changés. \nTous ensemble sur la nue, \nEn un clin d’œil nous monterons, \nPour être avec Lui toujours. \nSeras-tu prêt?",
                "Travaillons pour notre Maître \nTandis qu’il fait encore jour, \nMoissonnons des âmes pour l’éternité! \nS’Il nous trouve à notre poste, \nPleins de zèle et pleins d’amour, \nQuand Il viendra nous chercher, \nNous serons prêts!"
            ]
        },
        {
            "songTitle": "BÉNISSONS DIEU, NOTRE ROI",
            "id": 88,
            "songId": 63,
            "chorus": "",
            "key": "Fa majeur",
            "author": "J. Neander (168O), Trad. J. Vincent",
            "enLyrics": [
                "Bénissons Dieu, notre Roi, \nLe puissant Roi de gloire! \nDe Ses bienfaits incessants, \nCélébrons la mémoire! \nEt qu’en tous lieux, \nSur la terre et dans les cieux, \nMontent les chants de louange!",
                "Bénissons Dieu, notre Roi, \nDont la main étendue, \nPorte Ses faibles enfants, \nComme l’aigle en la nue! \nIl nous guérit. \nSon pouvoir est infini, \nIl nous remplit d’allégresse.",
                "Bénissons Dieu, notre Roi! \nCélébrons Ses louanges, \nCar Il demeure à jamais \nQuand tout passe et tout change. \nIl nous entend: \nAdressons-Lui notre chant, \nUnis aux chœurs de Ses anges!"
            ]
        },
        {
            "songTitle": "SEIGNEUR, QUE N’ES-JE MILLE VOIX",
            "id": 436,
            "songId": 64,
            "chorus": "",
            "key": "Sol majeur",
            "author": "Ch. Wesley (1739), R. Saillens, T. Jarman – 1821",
            "enLyrics": [
                "Pour chanter tes louanges, (bis) \nEt faire monter jusqu’aux anges \nLes gloires de ta croix ! (ter)",
                "Jésus, mon Seigneur et mon Dieu, \nQue ton souffle m’anime (bis) \nPour que par moi ton nom sublime \nRetentisse en tout lieu ! (ter)",
                "Doux nom qui fait tarir nos pleurs \nIneffable harmonie, (bis) \nTu répands la joie et la vie \nEt la paix dans nos cœurs ! (bis)",
                "Désormais, je n’ai plus d’effroi, \nAucun mal ne m’accable, (bis) \nTon sang rend pur le plus coupable : \nTon sang coula pour moi. (ter) \nGet the app here for more hymn lyrics:"
            ]
        },
        {
            "songTitle": "DIEU TOUT PUISSANT",
            "id": 23,
            "songId": 65,
            "chorus": "",
            "key": "Si ♭ majeur",
            "author": "Hector Arnéra, Carl Boberg (1885)",
            "enLyrics": [
                "Dieu tout puissant, \nQuand mon cœur considère, \nTout l’univers créé par Ton pouvoir; \nLe ciel d’azur, les éclairs, le tonnerre, \nLe clair matin ou les ombres du soir: \nDe tout mon être, \nAlors s’élève un chant, \nDieu tout puissant, que Tu es grand.",
                "Quand par les bois ou la forêt profonde, \nJ’erre et j’entends \nTous les oiseaux chanter; \nQuand sur les monts, \nLa source avec son onde, \nLivre au zéphyr, \nson chant doux et léger; \nMon cœur heureux \nS’écrie à chaque instant, \nÔ Dieu d’amour, que Tu es grand.",
                "Et quand je songe, ô sublime mystère! \nQu’un Dieu si grand a pu penser à moi; \nQue Son cher Fils est devenu mon Frère, \nEt que je suis l’héritier du grand Roi. \nAlors mon cœur redit la nuit, le jour: \nQue Tu es bon, \nO Dieu d’amour.",
                "Quand mon Sauveur éclatant de lumière, \nSe lèvera de Son trône éternel, \nEt que laissant les douleurs de la terre, \nJe pourrai voir les splendeurs de Son ciel: \nJe redirai dans Son divin séjour, \nRien n’est plus grand \nQue Son Amour."
            ]
        },
        {
            "songTitle": "L’AMOUR DE DIEU DE LOIN",
            "id": 89,
            "songId": 66,
            "chorus": "L’amour de Dieu si fort si tendre, \nEst un amour sans fin: \nTel est le chant que font entendre, \nLes anges et les saints.",
            "key": "Mi ♭ majeur",
            "author": "Frederick M. Lehman (1917), Claire-Lise de Benoit",
            "enLyrics": [
                "L’amour de Dieu de loin surpasse, \nCe qu’en peut dire un cœur humain. \nIl est plus grand que les espaces, \nMême en l’abîme, il nous atteint. \nPour le péché de notre monde, \nDieu nous donna Jésus. \nIl nous pardonne, oh paix profonde, \nIl sauve les perdus.",
                "Et si le monde un jour chancelle, \nAvec ses trônes et ses rois, \nQuand trembleront tous les rebelles, \nSoudain saisis d’un grand effroi, \nDe Dieu l’amour que rien ne lasse, \nPour nous encore vivra. \nC’est le miracle de la grâce. \nAmen, alléluia.",
                "Versez de l’encre dans les ondes; \nChangez le ciel en parchemin; \nTendez la plume à tout le monde; \nEt que chacun soit écrivain. \nVous dire tout l’amour du Père, \nFerait tarir les eaux, \nEt remplirait la place entière, \nSur ces divins rouleaux."
            ]
        },
        {
            "songTitle": "DIEU, TA FIDÉLITÉ",
            "id": 62,
            "songId": 67,
            "chorus": "Dieu, Ta fidélité, \nTon immense bonté, \nSe renouvellent envers moi \nChaque jour. \nTous mes besoins, \nC’est Ta main qui les comble. \nDieu, Ta fidélité dure à toujours.",
            "key": "Ré majeur",
            "author": "Thomas Chisholm (1923), William M. Runyan (1923)",
            "enLyrics": [
                "Dieu, Ta fidélité va jusqu’aux nues; \nPlus vaste est Ton amour que l’horizon. \nTa tendre main est toujours étendue; \nInépuisable est Ta compassion.",
                "L’été et l’automne, \nLe printemps et l’hiver, \nSoleil, lune et étoiles \nDans leurs courses, \nSe joignent à la nature’ pour témoigner, \nDe Ta fidélité grande et immense.",
                "Ta joie et Ton pardon \nEn abondance, \nTa présence en mon cœur, \nTa chaude voix, \nTa force à chaque pas, \nTon espérance, \nPar Ta fidélité tout est à moi."
            ]
        },
        {
            "songTitle": "QUEL REPOS CÉLESTE",
            "id": 36,
            "songId": 68,
            "chorus": "Quel repos, quel repos, (x2) \nQuel repos, quel céleste repos!",
            "key": "Ré ♭ majeur",
            "author": "Philip-Paul Bliss, Amélie Humbert (1851-1936)",
            "enLyrics": [
                "Quel repos céleste \nJésus, d’être à Toi! \nÀ Toi pour la mort et la vie, \nDans les jours mauvais \nDe chanter avec foi: \nTout est bien, ma paix est infinie!",
                "Quel repos céleste, \nMon fardeau n’est plus! \nLibre par le sang du Calvaire, \nTous mes ennemis, \nJésus les a vaincus, \nGloire et louange à Dieu notre Père!",
                "Quel repos céleste! Tu conduis mes pas, \nTu me combles de Tes richesses, \nDans Ton grand amour, \nchaque jour Tu sauras \nDéployer envers moi Tes tendresses.",
                "Quel repos céleste, \nQuand enfin, Seigneur, \nAuprès de Toi j’aurai ma place, \nAprès les travaux, \nLes combats, la douleur, \nÀ jamais je pourrai voir Ta face!"
            ]
        },
        {
            "songTitle": "JE NE SAIS POURQUOI",
            "id": "41a",
            "songId": 69,
            "chorus": "Mais je sais qu’en lui j’ai la vie, \nIl m’a sauvé dans son amour; \nEt gardé par sa main meurtrie, \nJ’attends l’heure de son retour.",
            "key": "Mi ♭ majeur",
            "author": "J. Granahan (1840-1907), G. Guillod 19e et 20e S.",
            "enLyrics": [
                "Je ne sais pourquoi dans sa grâce \nJésus m’a tant aimé, \nPourquoi par Son sang Il efface \nMa dette, mon péché.",
                "Je ne sais comment la lumière \nÉclaire tout mon cœur, \nComment je compris ma misère \nEt reçus mon Sauveur!",
                "Je ne sais quelle est la mesure \nDe joie et de douleur, \nQue pour moi, faible créature, \nRéserve mon Sauveur.",
                "Je ne sais quand de la victoire, \nL’heure enfin sonnera, \nQuand l’Agneau, l’Époux, dans sa gloire, \nAvec lui me prendra."
            ]
        },
        {
            "songTitle": "PÈLERIN J’ERRAIS LOIN",
            "id": 90,
            "songId": 70,
            "chorus": "Oui, le bonheur et la grâce, \nM’accompagneront \nTous les jours, \nTous les jours de ma vie. (x2) \nJ’habiterai dans la maison de l’Éternel; \nJ’habiterai dans la maison du Père. \nOui, le bonheur et la grâce M’accompagneront \nTous les jours, \nTous les jours de ma vie.",
            "key": "Mi ♭ majeur",
            "author": "John W. Peterson (1958); Alfred B. Smith (1958)",
            "enLyrics": [
                "Pèlerin j’errais loin de mon Père, \nDans le froid de la nuit du péché. \nMaintenant je vis dans la lumière \nDu bon Berger qui m’a retrouvé.",
                "Il me conduit près des sources calmes, \nJe me repose dans Son amour; \nChaque jour Il restaure mon âme, \nEt dans Ses sentiers j’ai le secours.",
                "Dans la vallée de l’ombre de la mort, \nJe ne crains aucun mal, Tu es là; \nJe suis environné de Ton bras fort, \nEt ma coupe déborde de joie."
            ]
        },
        {
            "songTitle": "JÉSUS QUITTA LE TRÔNE",
            "id": 51,
            "songId": 71,
            "chorus": "Oh! Oui, c’est vrai! Je sais que c’est vrai! \n'Il est écrit': Cela suffit! \nQue Jésus m’aime! Oh! Bonheur \nsuprême! \nLa Bible me le dit!",
            "key": "Sol majeur",
            "author": "E.Schürer, P.P. Bliss (1870)",
            "enLyrics": [
                "Jésus quitta le trône de son Père \nEt descendit ici-bas sur la terre; \nIl accepta la crèche pour berceau, \nLui, Roi des rois, le Fils du Dieu Très-Haut!",
                "En tous les lieux portant la délivrance, \nFaisant le bien, guérissant la souffrance, \nIl pardonnait au pécheur repentant, \nIl bénissait jusqu’aux petits enfants.",
                "Il fut cloué sur la croix méprisable, \nLui, Juste et Saint, \nMourut pour moi coupable. \nPour me sauver, son sang fut répandu; \nC’est pourquoi j’aime le Seigneur Jésus!",
                "Si tu me demandais comment je sais \nQue Jésus m’aime’, c’est le plus simple fait. \nSon Saint-Esprit témoigne dans mon cœur \nEn criant puissamment: “Abba mon Père”.",
                "Plus que vainqueur Il sortit de la tombe, \nGloire à l’Agneau, divin Sauveur du monde! \nIl règne au ciel, intercède pour moi, \nEt vient bientôt me chercher: Je le crois!"
            ]
        },
        {
            "songTitle": "IL VA VENIR, LE SEIGNEUR",
            "id": 91,
            "songId": 72,
            "chorus": "Gloire à Toi seul, Seigneur Jésus, \nGloire à jamais, gloire à Ton nom! \nDe Ton beau ciel je ne sortirai plus, \nEt pour toujours j’exalterai Ton nom.",
            "key": "La ♭ majeur",
            "author": "Chas. H. Gabriel (1900)",
            "enLyrics": [
                "Il va venir, le Seigneur que j’adore; \nBientôt Sa voix retentira du ciel. \nÀ mes regards l’horizon se colore \nDes purs rayons du soleil éternel.",
                "Maison du Père, \nOù Ton amour m’appelle, \nSainte cité, demeure des Élus; \nLes lieux qu’éclaire une gloire éternelle, \nMe sont ouverts par Toi-même, ô Jésus!",
                "Bonheur ineffable! Quand dans Ta gloire, \nAux yeux des rachetés Tu paraîtras, \nJésus, avec le cri de la victoire, \nPrès de Toi, pour toujours Tu me prendras."
            ]
        },
        {
            "songTitle": "RESTE AVEC NOUS ",
            "id": 35,
            "songId": 73,
            "chorus": "",
            "key": "Mi ♭ majeur",
            "author": "W.H. Monk , Paroles F. Chaponnière (1881)",
            "enLyrics": [
                "Reste avec nous, Seigneur, le jour décline, \nLa nuit s’approche et nous menace tous; \nNous implorons Ta présence divine: \nReste avec nous, Seigneur, reste avec nous.",
                "En Toi nos cœurs ont salué leur Maître, \nEn Toi notre âme a trouvé son Époux; \nÀ Ta lumière elle se sent renaître; \nReste avec nous, Seigneur, reste avec nous.",
                "Dans nos combats si ta main nous délaisse, \nSatan vainqueur nous tiendra sous ses coups; \nQue ta puissance arme notre faiblesse; \nReste avec nous, Seigneur, reste avec nous.",
                "Sous Ton regard la joie est sainte et bonne, \nPrès de Ton cœur les pleurs même sont doux; \nSoit que Ta main nous frappe \nou nous couronne, \nReste avec nous, Seigneur, reste avec nous."
            ]
        },
        {
            "songTitle": "À DIEU SOIT LA GLOIRE",
            "id": 1,
            "songId": 74,
            "chorus": "Gloire à Dieu! (x2) \nTerre écoute Sa voix! \nGloire à Dieu! (x2) \nMonde réjouis-toi! \nOh! Venez au Père, \nJésus est vainqueur; \nQue toute la terre \nChante en Son honneur!",
            "key": "Fa majeur",
            "author": "Fanny J. Crosby (1975)",
            "enLyrics": [
                "À Dieu soit la gloire, \nPar Son grand amour, \nDans mon âme noire, \nS’est levé le jour. \nJésus, à ma place, \nMourut sur la croix, \nIl m’offre Sa grâce et je la reçois!",
                "Parfaite rédemption, \nChrist a racheté \nPour Dieu par Son sang \nLes gens de toute tribu; \nCelui qui de sa bouche \nConfesse Jésus, \nEt qui croit dans son cœur, \nsera pardonné.",
                "De Jésus la joie \nremplit notre cœur; \nQu’importe qu’on voie tout notre bonheur, \nSelon Sa promesse Jésus changera \nDeuil en allégresse, quand Il reviendra."
            ]
        },
        {
            "songTitle": "LE FILS DE DIEU, LE SEIGNEUR JESUS,",
            "id": "437a",
            "songId": 75,
            "chorus": "Parce qu’il vit \nJe n’es rien à craindre, \nMes lendemains sont assurés. \nEntre ses mains, \nIl tien ma vie. \nPour ce temps et l’éternité \nJe sais qu’il vit.",
            "key": "La ♭ majeur",
            "author": "Gloria Gaither (1971); Author: Bill Gaither (1971)",
            "enLyrics": [
                "Pour racheter un monde perdu, \nDonna sa vie sur le Calvaire. \nEt de la mort et du tombeau \nIl est vainqueur.",
                "Ce jour béni, ce beau message \nEt l’entendis dans ma misère, \nEt j’acceptai le Seigneur Jésus \nEt avec lui, je vivrai \nPour l’éternité"
            ]
        },
        {
            "songTitle": "QUEL SAUVEUR MERVEILLEUX",
            "id": "92a",
            "songId": 76,
            "chorus": "Attaché à la croix pour moi, \nAttaché à la croix pour moi, \nII a pris mon péché, II m'a délivré, \nAttaché à la croix pour moi.",
            "key": "Mi ♭ majeur",
            "author": "Frederick Arthur Graves, (1906) , Algot Edlund",
            "enLyrics": [
                "Quel Sauveur merveilleux je possède, \nII s’est sacrifié pour moi. \nEt Sa vie innocente, Il cède, \nPour mourir sur l'infâme bois.",
                "Il renonce un moment à son trône \nPour le plan rédempteur de Dieu. \nDéposant pour moi sa couronne, \nUn tel prix pour me rendre heureux !",
                "Méprisé, rejeté par les hommes, \nPour mes iniquités brisées, \nIl me dit, « vois combien je t’aime », \nEt il me meurt pour me racheter.",
                "Le salut accompli sur la terre, \nMon sauveur remonta au ciel, \nMais bientôt, il va réapparaître, \nMon bonheur sera éternel."
            ]
        },
        {
            "songTitle": "REDEMPTEUR DU MONDE,",
            "id": 438,
            "songId": 77,
            "chorus": "Merci notre Père, \nD’avoir donné Jésus, ton fils, \nEt d’envoyé ta lumière \nPar le Saint-Esprit.",
            "key": "Do majeur",
            "author": "Keith Gordon Green ( 1953 - 1982)",
            "enLyrics": [
                "Jésus-Christ, Fils de Dieu, \nTa joie et ta paix m’inondent, \nToi, l’agneau venu des cieux.",
                "Rédempteur du monde, \nPour nous, tu fus crucifié, \nTon amour, ta grâce abondent, \nO glorieux ressuscité.",
                "Un jour, dans la gloire, \nJe verrai ta face, \nJe vivrai sous ton regard, \nSauvé par ta grâce."
            ]
        },
        {
            "songTitle": "BIENTÔT JÉSUS ",
            "id": 49,
            "songId": 78,
            "chorus": "Nous avons la victoire! \nNous vivrons avec Jésus dans le ciel! \nÀ Toi seul la gloire! \nOh! Viens bientôt, Emmanuel!",
            "key": "Do majeur",
            "author": "H.E. Alexander (1883-1957), E. Wilson (1865-1942)",
            "enLyrics": [
                "Bientôt Jésus va nous prendre, \nAuprès de Lui dans le ciel; \nIl nous a dit de L’attendre, \nJusqu'au jour de Son appel.",
                "Péchés, travaux et souffrances, Cesseront et pour toujours. \nDevant Sa sainte présence, \nNous chanterons Son amour.",
                "Combattons avec courage, \nAttendant ce jour heureux. \nEt chantons malgré l’orage: \nNous serons victorieux!",
                "Et si l’ennemi fait rage, \nComptons toujours sur Jésus. \nAvec Lui pas de naufrage; \nLe port est déjà en vue!"
            ]
        },
        {
            "songTitle": "ESPERE EN DIEU",
            "id": 127,
            "songId": 79,
            "chorus": "Espère en Dieu quand la tempête \nContre la nef jette ses flots. \nUn mot vainqueur déjà s’apprête \nÀ commander paix et repos.",
            "key": "La ♭ majeur",
            "author": "E. Bonnard, Ch. H. Gabriel (1856-1932)",
            "enLyrics": [
                "Espère en Dieu quand la nuit sombre \nVoile le ciel et l’horizon. \nJamais là-haut ne règne l’ombre, \nLà-haut t’attend une maison.",
                "Espère en Dieu quand la souffrance, \nBrisant ton corps, trouble ton cœur, \nChez lui jamais l’indifférence \nNe le distrait de ton malheur. \nEspère en Dieu quand sonne l’heure \nD’abandonner les biens d’en bas. \nCrois aux trésors de sa demeure, \nCar son amour t’ouvre ses bras.",
                "Espère en Dieu quand on t’oublie \nOu qu’on te raille avec dédain. \nPour te sauver, jamais ne plie, \nVa plutôt seul sur ton chemin. \nEspère en Dieu quand ton pied glisse \nSous les efforts du tentateur \nSaisis la main libératrice \nQui te rendra toujours vainqueur."
            ]
        },
        {
            "songTitle": "COMPTE LES BIENFAITS",
            "id": 94,
            "songId": 80,
            "chorus": "",
            "key": "Mi ♭ / Ré majeur",
            "author": "J. Oatman (1897), E. O. Excell (1897), M. Perrenoud",
            "enLyrics": [
                "Quand le vol de la tempête \nVient assombrir ton ciel bleu, \nAu lieu de baisser la tête, \nCompte les bienfaits de Dieu. \nCompte les bienfaits de Dieu, \nMets-les tous devant tes yeux, \nTu verras, en adorant, \nCombien le nombre en est grand.",
                "Quand sur la route glissante, \nTu chancelles sous ta croix, \nPense à cette main puissante \nQui t’a béni tant de fois. \nCompte les bienfaits de Dieu, \nMets-les tous devant tes yeux, \nTu verras, en adorant, \nCombien le nombre en est grand.",
                "Si tu perds dans le voyage \nPlus d’un cher et doux trésor, \nPense au divin héritage \nQui, là-haut, te reste encor.",
                "Bénis donc, bénis sans cesse \nCe Père qui, chaque jour, \nRépand sur toi la richesse \nDe Son merveilleux amour. Compte les bienfaits de Dieu, \nMets-les tous devant tes yeux, \nTu verras, en adorant, \nCombien le nombre en est grand."
            ]
        }
    ]
}